mopidy_multisonic/__init__.py
mopidy_multisonic/backend.py
mopidy_multisonic/browser.py
mopidy_multisonic/cache.py
mopidy_multisonic/ext.conf
mopidy_multisonic/httpclient.py
mopidy_multisonic/library.py
mopidy_multisonic/lookup.py
mopidy_multisonic/playback.py
mopidy_multisonic/searcher.py
mopidy_multisonic/uri_parser.py
Mopidy_Multisonic-0.5.2.dist-info/LICENSE
Mopidy_Multisonic-0.5.2.dist-info/METADATA
Mopidy_Multisonic-0.5.2.dist-info/WHEEL
Mopidy_Multisonic-0.5.2.dist-info/entry_points.txt
Mopidy_Multisonic-0.5.2.dist-info/top_level.txt
Mopidy_Multisonic-0.5.2.dist-info/RECORD
