Metadata-Version: 2.1
Name: Mopidy-Multisonic
Version: 0.5.2
Summary: A mopidy backend provider for multisonic services
Home-page: https://sr.ht/~reedwade/mopidy-multisonic/
Author: ReedWade
Author-email: <reedwade@misterbanal.net>
License: Apache License, Version 2.0
Platform: UNKNOWN
Classifier: Environment :: No Input/Output (Daemon)
Classifier: Intended Audience :: End Users/Desktop
Classifier: License :: OSI Approved :: Apache Software License
Classifier: Operating System :: OS Independent
Classifier: Programming Language :: Python :: 3
Classifier: Topic :: Multimedia :: Sound/Audio :: Players
Requires-Python: >=3.7
Requires-Dist: setuptools
Requires-Dist: Mopidy (>=0.14)
Requires-Dist: Pykka (>=1.1)
Provides-Extra: dev
Requires-Dist: black ; extra == 'dev'
Requires-Dist: check-manifest ; extra == 'dev'
Requires-Dist: flake8 ; extra == 'dev'
Requires-Dist: flake8-bugbear ; extra == 'dev'
Requires-Dist: flake8-import-order ; extra == 'dev'
Requires-Dist: isort[pyproject] ; extra == 'dev'
Requires-Dist: twine ; extra == 'dev'
Requires-Dist: wheel ; extra == 'dev'
Requires-Dist: pytest ; extra == 'dev'
Requires-Dist: pytest-cov ; extra == 'dev'
Provides-Extra: lint
Requires-Dist: black ; extra == 'lint'
Requires-Dist: check-manifest ; extra == 'lint'
Requires-Dist: flake8 ; extra == 'lint'
Requires-Dist: flake8-bugbear ; extra == 'lint'
Requires-Dist: flake8-import-order ; extra == 'lint'
Requires-Dist: isort[pyproject] ; extra == 'lint'
Provides-Extra: release
Requires-Dist: twine ; extra == 'release'
Requires-Dist: wheel ; extra == 'release'
Provides-Extra: test
Requires-Dist: pytest ; extra == 'test'
Requires-Dist: pytest-cov ; extra == 'test'
